LICENSE.txt
MANIFEST.in
README.md
setup.py
cbrain/__init__.py
cbrain/__main__.py
cbrain/client.py
cbrain/comm.py
cbrain/comm_min.py
cbrain/config.py
cbrain/graph.py
cbrain/main.py
cbrain/obj.py
cbrain/setup.py
cbrain/solution.py
cbrain.egg-info/PKG-INFO
cbrain.egg-info/SOURCES.txt
cbrain.egg-info/dependency_links.txt
cbrain.egg-info/entry_points.txt
cbrain.egg-info/not-zip-safe
cbrain.egg-info/requires.txt
cbrain.egg-info/top_level.txt
cbrain/static/favicon.ico