Metadata-Version: 2.1
Name: cbrain
Version: 1.1.12
Summary: cBrian.io client to exchange reusable computational components and workflows
Home-page: https://cKnowledge.io
Author: Grigori Fursin
Author-email: Grigori.Fursin@cTuning.org
License: Apache Software License (Apache 2.0)
Keywords: reproducible benchmarking,customizable benchmarking,portable workflows,reusable computational components,reproducibility,collaborative experiments,automation,optimization,co-design,collective knowledge
Platform: UNKNOWN
Classifier: Development Status :: 4 - Beta
Classifier: Programming Language :: Python :: 2.7
Classifier: Programming Language :: Python :: 3
Classifier: Intended Audience :: Developers
Classifier: Intended Audience :: Education
Classifier: Intended Audience :: End Users/Desktop
Classifier: Intended Audience :: Information Technology
Classifier: Intended Audience :: Science/Research
Requires-Python: >=2.7
